dxlirflowservice/__init__.py
dxlirflowservice/__main__.py
dxlirflowservice/_version.py
dxlirflowservice/app.py
dxlirflowservice/requesthandlers.py
dxlirflowservice/_config/__init__.py
dxlirflowservice/_config/app/__init__.py
dxlirflowservice/_config/app/dxlclient.config
dxlirflowservice/_config/app/irflowservice.config
dxlirflowservice/_config/app/logging.config
dxlirflowservice/_config/sample/__init__.py
dxlirflowservice/_config/sample/dxlclient.config
dxlirflowservice-1.1.0.dist-info/LICENSE
dxlirflowservice-1.1.0.dist-info/METADATA
dxlirflowservice-1.1.0.dist-info/WHEEL
dxlirflowservice-1.1.0.dist-info/top_level.txt
dxlirflowservice-1.1.0.dist-info/RECORD
