Metadata-Version: 2.1
Name: dxlirflowservice
Version: 1.1.0
Summary: dxlsyncurityirflowservice
Home-page: https://www.syncurity.net
Author: JP Bourget, Syncurity
License: Apache 2.0
Keywords: security,syncurity,ir-flow,orchestration,opendxl
Platform: UNKNOWN
Classifier: Programming Language :: Python
Classifier: Programming Language :: Python :: 2
Classifier: Programming Language :: Python :: 2.7
Classifier: Programming Language :: Python :: 3
Classifier: Programming Language :: Python :: 3.6
Requires-Python: >=2.7.9,<3
Requires-Dist: requests (==2.20.0)
Requires-Dist: irflow-client (>=1.5.6)
Requires-Dist: dxlbootstrap (>=0.2.0)
Requires-Dist: dxlclient (>=4.1.0.184)
